audmodel/__init__.py
audmodel/core/__init__.py
audmodel/core/api.py
audmodel/core/backend.py
audmodel/core/config.py
audmodel/core/conftest.py
audmodel/core/define.py
audmodel/core/lock.py
audmodel/core/repository.py
audmodel/core/utils.py
audmodel-1.4.0.dist-info/licenses/LICENSE
audmodel-1.4.0.dist-info/METADATA
audmodel-1.4.0.dist-info/WHEEL
audmodel-1.4.0.dist-info/top_level.txt
audmodel-1.4.0.dist-info/RECORD
