Metadata-Version: 2.4
Name: audmodel
Version: 1.4.0
Summary: Publish and load models
Author-email: Johannes Wagner <jwagner@audeering.com>, Hagen Wierstorf <hwierstorf@audeering.com>
License-Expression: MIT
Project-URL: repository, https://gitlab.audeering.com/tools/audmodel
Project-URL: documentation, http://tools.pp.audeering.com/audmodel/
Keywords: machine learning,model,Artifactory
Classifier: Development Status :: 5 - Production/Stable
Classifier: Intended Audience :: Science/Research
Classifier: Intended Audience :: Developers
Classifier: Operating System :: OS Independent
Classifier: Programming Language :: Python
Classifier: Programming Language :: Python :: 3
Classifier: Programming Language :: Python :: 3.10
Classifier: Programming Language :: Python :: 3.11
Classifier: Programming Language :: Python :: 3.12
Classifier: Programming Language :: Python :: 3.13
Classifier: Programming Language :: Python :: 3.14
Classifier: Topic :: Scientific/Engineering
Requires-Python: >=3.10
License-File: LICENSE
Requires-Dist: audbackend[all]>=2.2.3
Requires-Dist: filelock
Requires-Dist: oyaml
Dynamic: license-file
